conwech/__init__.py
conwech/__main__.py
conwech/_exceptions.py
conwech/_regexlib.py
conwech/functions.py
conwech/lexicon.py
conwech-2020.8.dist-info/LICENSE
conwech-2020.8.dist-info/METADATA
conwech-2020.8.dist-info/WHEEL
conwech-2020.8.dist-info/entry_points.txt
conwech-2020.8.dist-info/top_level.txt
conwech-2020.8.dist-info/RECORD
