Metadata-Version: 2.1
Name: conwech
Version: 2020.8
Summary: A module for reading & writing numbers using the Conway-Wechsler naming system
Home-page: https://github.com/KCATurner/conwech.git
Author: Kevin Turner
Author-email: kct0004@auburn.edu
License: UNKNOWN
Platform: UNKNOWN
Classifier: License :: OSI Approved :: MIT License
Classifier: Operating System :: OS Independent
Requires-Python: >=3.4
Requires-Dist: colorama
